sticht/__init__.py
sticht/exceptions.py
sticht/py.typed
sticht/signalfx.py
sticht/slack.py
sticht/state_machine.py
sticht/rollbacks/__init__.py
sticht/rollbacks/base.py
sticht/rollbacks/metrics.py
sticht/rollbacks/slo.py
sticht/rollbacks/soaconfigs.py
sticht/rollbacks/types.py
sticht/rollbacks/sources/__init__.py
sticht/rollbacks/sources/splunk.py
sticht-1.2.1.dist-info/LICENSE
sticht-1.2.1.dist-info/METADATA
sticht-1.2.1.dist-info/WHEEL
sticht-1.2.1.dist-info/top_level.txt
sticht-1.2.1.dist-info/RECORD
